superturtle/__init__.py
superturtle/animation.py
superturtle/easing.py
superturtle/fancy_drawing.py
superturtle/image.py
superturtle/movement.py
superturtle/stroke.py
superturtle/test.py
superturtle-1.2.0.dist-info/METADATA
superturtle-1.2.0.dist-info/WHEEL
superturtle-1.2.0.dist-info/RECORD
