Metadata-Version: 2.3
Name: superturtle
Version: 1.2.0
Summary: Extensions to Python's turtle
License: MIT
Author: Chris Proctor
Author-email: chris@chrisproctor.net
Requires-Python: >=3.10,<4.0
Classifier: License :: OSI Approved :: MIT License
Classifier: Programming Language :: Python :: 3
Classifier: Programming Language :: Python :: 3.10
Classifier: Programming Language :: Python :: 3.11
Classifier: Programming Language :: Python :: 3.12
Classifier: Programming Language :: Python :: 3.13
Requires-Dist: svg-turtle (>=1.0.0,<2.0.0)
